README.md
setup.py
src/arvo/__init__.py
src/arvo/isorhythm.py
src/arvo/minimalism.py
src/arvo/scales.py
src/arvo/sequences.py
src/arvo/tintinnabuli.py
src/arvo/tools.py
src/arvo/transformations.py
src/arvo.egg-info/PKG-INFO
src/arvo.egg-info/SOURCES.txt
src/arvo.egg-info/dependency_links.txt
src/arvo.egg-info/requires.txt
src/arvo.egg-info/top_level.txt