Metadata-Version: 1.0
Name: arvo
Version: 0.3.0
Summary: Python library for procedural music composition
Home-page: https://github.com/georgesdimitrov/arvo
Author: Georges Dimitrov
Author-email: georges.dimitrov@gmail.com
License: MIT
Platform: UNKNOWN
